adabound/__init__.py
adabound/adabound.py
adabound-0.0.5.dist-info/METADATA
adabound-0.0.5.dist-info/RECORD
adabound-0.0.5.dist-info/WHEEL
adabound-0.0.5.dist-info/top_level.txt
