Metadata-Version: 2.1
Name: adabound
Version: 0.0.5
Summary: AdaBound optimization algorithm, build on PyTorch.
Home-page: https://github.com/Luolc/AdaBound
Author: Liangchen Luo
Author-email: luolc.witty@gmail.com
License: Apache
Keywords: machine learning,deep learning
Platform: UNKNOWN
Classifier: Intended Audience :: Science/Research
Classifier: Development Status :: 3 - Alpha
Classifier: License :: OSI Approved :: Apache Software License
Classifier: Programming Language :: Python :: 3.6
Classifier: Programming Language :: Python :: 3.7
Classifier: Topic :: Scientific/Engineering :: Artificial Intelligence
Requires-Python: >=3.6.0
Requires-Dist: torch (>=0.4.0)
